topsis_ritigya_102303467/__init__.py
topsis_ritigya_102303467/cli.py
topsis_ritigya_102303467/core.py
topsis_ritigya_102303467-1.0.0.dist-info/licenses/LICENSE
topsis_ritigya_102303467-1.0.0.dist-info/METADATA
topsis_ritigya_102303467-1.0.0.dist-info/WHEEL
topsis_ritigya_102303467-1.0.0.dist-info/entry_points.txt
topsis_ritigya_102303467-1.0.0.dist-info/top_level.txt
topsis_ritigya_102303467-1.0.0.dist-info/RECORD
