Metadata-Version: 2.4
Name: Topsis-Ritigya-102303467
Version: 1.0.0
Summary: TOPSIS implementation as a Python package
Author: Ritigya
Author-email: rsingh7_be23@thapar.edu
Requires-Python: >=3.7
License-File: LICENSE
Requires-Dist: pandas
Requires-Dist: numpy
Dynamic: author
Dynamic: author-email
Dynamic: description
Dynamic: description-content-type
Dynamic: license-file
Dynamic: requires-dist
Dynamic: requires-python
Dynamic: summary
